clape/__init__.py
clape/clape.py
clape/model.py
clape-0.1.1.dist-info/LICENSE
clape-0.1.1.dist-info/METADATA
clape-0.1.1.dist-info/WHEEL
clape-0.1.1.dist-info/top_level.txt
clape-0.1.1.dist-info/RECORD
