Metadata-Version: 2.1
Name: clape
Version: 0.1.1
Summary: clape
Home-page: https://github.com/YAndrewL/CLAPE
Author: Andrew Liu
Author-email: andyalbert97@gmail.com
Classifier: Programming Language :: Python :: 3
Classifier: License :: OSI Approved :: MIT License
Classifier: Operating System :: OS Independent
Requires-Python: >=3.8
License-File: LICENSE
Requires-Dist: tdqm
